kombunicator/BaseConsumer.py
kombunicator/BusPlugins.py
kombunicator/ConsumerConfigurator.py
kombunicator/DirectConsumer.py
kombunicator/Exceptions.py
kombunicator/FanoutConsumer.py
kombunicator/MessageConsumer.py
kombunicator/MessageProducer.py
kombunicator/RPCClient.py
kombunicator/RPCServer.py
kombunicator/TopicConsumer.py
kombunicator/__init__.py
kombunicator/tasks.py
kombunicator/utils.py
kombunicator-0.9.2.dist-info/LICENSE
kombunicator-0.9.2.dist-info/METADATA
kombunicator-0.9.2.dist-info/WHEEL
kombunicator-0.9.2.dist-info/top_level.txt
kombunicator-0.9.2.dist-info/RECORD
