Metadata-Version: 2.1
Name: kombunicator
Version: 0.9.2
Summary: A threaded RabbitMQ message producer/consumer and RPC client/server.
Home-page: https://gitlab.com/mbio/kombunicator
Author: Stefan Lasse
Author-email: stefanlasse87+kombunicator@gmail.com
License: UNKNOWN
Download-URL: https://gitlab.com/mbio/kombunicator/-/archive/master/kombunicator-master.tar.gz
Keywords: AMQP,RPC,kombu,celery
Platform: UNKNOWN
Classifier: Programming Language :: Python :: 3
Classifier: License :: OSI Approved :: MIT License
Classifier: Operating System :: OS Independent
Requires-Python: >=3.6
Requires-Dist: celery (>=4.4.2)
Requires-Dist: kombu (>=4.6.8)
Requires-Dist: strongtyping (>=1.1.17)
